<profile>

<ReportVersion>
<Version>2024.2</Version>
</ReportVersion>

<UserAssignments>
<unit>ns</unit>
<ProductFamily>zynquplus</ProductFamily>
<Part>xczu7ev-ffvc1156-2-e</Part>
<TopModelName>upconv_core_top_ucb3</TopModelName>
<TargetClockPeriod>3.33</TargetClockPeriod>
<ClockUncertainty>0.90</ClockUncertainty>
<FlowTarget>vivado</FlowTarget>
</UserAssignments>

<PerformanceEstimates>
<PipelineType>no</PipelineType>
<SummaryOfTimingAnalysis>
<unit>ns</unit>
<EstimatedClockPeriod>2.877</EstimatedClockPeriod>
</SummaryOfTimingAnalysis>
<SummaryOfOverallLatency>
<unit>clock cycles</unit>
<Best-caseLatency>4710143</Best-caseLatency>
<Average-caseLatency>15214335</Average-caseLatency>
<Worst-caseLatency>25712383</Worst-caseLatency>
<Best-caseRealTimeLatency>15.699 ms</Best-caseRealTimeLatency>
<Average-caseRealTimeLatency>50.709 ms</Average-caseRealTimeLatency>
<Worst-caseRealTimeLatency>85.699 ms</Worst-caseRealTimeLatency>
<Interval-min>4710144</Interval-min>
<Interval-max>25712384</Interval-max>
</SummaryOfOverallLatency>
<SummaryOfLoopLatency>
<ROW_LOOP>
<Slack>2.43</Slack>
<TripCount>127</TripCount>
<Latency>
<range>
<min>4673346</min>
<max>25511506</max>
</range>
</Latency>
<AbsoluteTimeLatency>
<range>
<min>15576261</min>
<max>85029848</max>
</range>
</AbsoluteTimeLatency>
<IterationLatency>
<range>
<min>36798</min>
<max>200878</max>
</range>
</IterationLatency>
<InstanceList>
</InstanceList>
</ROW_LOOP>
</SummaryOfLoopLatency>
<SummaryOfViolations>
<IssueType>-</IssueType>
<ViolationType>-</ViolationType>
<SourceLocation>../gen/Hls_Layers_UpConv.tpp:325~../gen/upconv_core_top_ucb3.cpp:41</SourceLocation>
<SummaryOfLoopViolations>
<ROW_LOOP>
<Name>ROW_LOOP</Name>
<IssueType>-</IssueType>
<ViolationType>-</ViolationType>
<SourceLocation>../gen/Hls_Layers_UpConv.tpp:333~../gen/upconv_core_top_ucb3.cpp:41</SourceLocation>
</ROW_LOOP>
</SummaryOfLoopViolations>
</SummaryOfViolations>
</PerformanceEstimates>

<AreaEstimates>
<Resources>
<BRAM_18K>148</BRAM_18K>
<DSP>670</DSP>
<FF>74497</FF>
<LUT>52637</LUT>
<URAM>20</URAM>
</Resources>
<AvailableResources>
<BRAM_18K>624</BRAM_18K>
<DSP>1728</DSP>
<FF>460800</FF>
<LUT>230400</LUT>
<URAM>96</URAM>
</AvailableResources>
</AreaEstimates>

<InterfaceSummary>
<RtlPorts>
<name>s_axi_control_AWVALID</name>
<Object>control</Object>
<Type>scalar</Type>
<IOProtocol>s_axi</IOProtocol>
<Dir>in</Dir>
<Bits>1</Bits>
<Attribute>unknown</Attribute>
<CType>int</CType>
<HasCtrl>1</HasCtrl>
</RtlPorts>
<RtlPorts>
<name>s_axi_control_AWREADY</name>
<Object>control</Object>
<Type>scalar</Type>
<IOProtocol>s_axi</IOProtocol>
<Dir>out</Dir>
<Bits>1</Bits>
<Attribute>unknown</Attribute>
<CType>int</CType>
<HasCtrl>1</HasCtrl>
</RtlPorts>
<RtlPorts>
<name>s_axi_control_AWADDR</name>
<Object>control</Object>
<Type>scalar</Type>
<IOProtocol>s_axi</IOProtocol>
<Dir>in</Dir>
<Bits>7</Bits>
<Attribute>unknown</Attribute>
<CType>int</CType>
<HasCtrl>1</HasCtrl>
</RtlPorts>
<RtlPorts>
<name>s_axi_control_WVALID</name>
<Object>control</Object>
<Type>scalar</Type>
<IOProtocol>s_axi</IOProtocol>
<Dir>in</Dir>
<Bits>1</Bits>
<Attribute>unknown</Attribute>
<CType>int</CType>
<HasCtrl>1</HasCtrl>
</RtlPorts>
<RtlPorts>
<name>s_axi_control_WREADY</name>
<Object>control</Object>
<Type>scalar</Type>
<IOProtocol>s_axi</IOProtocol>
<Dir>out</Dir>
<Bits>1</Bits>
<Attribute>unknown</Attribute>
<CType>int</CType>
<HasCtrl>1</HasCtrl>
</RtlPorts>
<RtlPorts>
<name>s_axi_control_WDATA</name>
<Object>control</Object>
<Type>scalar</Type>
<IOProtocol>s_axi</IOProtocol>
<Dir>in</Dir>
<Bits>32</Bits>
<Attribute>unknown</Attribute>
<CType>int</CType>
<HasCtrl>1</HasCtrl>
</RtlPorts>
<RtlPorts>
<name>s_axi_control_WSTRB</name>
<Object>control</Object>
<Type>scalar</Type>
<IOProtocol>s_axi</IOProtocol>
<Dir>in</Dir>
<Bits>4</Bits>
<Attribute>unknown</Attribute>
<CType>int</CType>
<HasCtrl>1</HasCtrl>
</RtlPorts>
<RtlPorts>
<name>s_axi_control_ARVALID</name>
<Object>control</Object>
<Type>scalar</Type>
<IOProtocol>s_axi</IOProtocol>
<Dir>in</Dir>
<Bits>1</Bits>
<Attribute>unknown</Attribute>
<CType>int</CType>
<HasCtrl>1</HasCtrl>
</RtlPorts>
<RtlPorts>
<name>s_axi_control_ARREADY</name>
<Object>control</Object>
<Type>scalar</Type>
<IOProtocol>s_axi</IOProtocol>
<Dir>out</Dir>
<Bits>1</Bits>
<Attribute>unknown</Attribute>
<CType>int</CType>
<HasCtrl>1</HasCtrl>
</RtlPorts>
<RtlPorts>
<name>s_axi_control_ARADDR</name>
<Object>control</Object>
<Type>scalar</Type>
<IOProtocol>s_axi</IOProtocol>
<Dir>in</Dir>
<Bits>7</Bits>
<Attribute>unknown</Attribute>
<CType>int</CType>
<HasCtrl>1</HasCtrl>
</RtlPorts>
<RtlPorts>
<name>s_axi_control_RVALID</name>
<Object>control</Object>
<Type>scalar</Type>
<IOProtocol>s_axi</IOProtocol>
<Dir>out</Dir>
<Bits>1</Bits>
<Attribute>unknown</Attribute>
<CType>int</CType>
<HasCtrl>1</HasCtrl>
</RtlPorts>
<RtlPorts>
<name>s_axi_control_RREADY</name>
<Object>control</Object>
<Type>scalar</Type>
<IOProtocol>s_axi</IOProtocol>
<Dir>in</Dir>
<Bits>1</Bits>
<Attribute>unknown</Attribute>
<CType>int</CType>
<HasCtrl>1</HasCtrl>
</RtlPorts>
<RtlPorts>
<name>s_axi_control_RDATA</name>
<Object>control</Object>
<Type>scalar</Type>
<IOProtocol>s_axi</IOProtocol>
<Dir>out</Dir>
<Bits>32</Bits>
<Attribute>unknown</Attribute>
<CType>int</CType>
<HasCtrl>1</HasCtrl>
</RtlPorts>
<RtlPorts>
<name>s_axi_control_RRESP</name>
<Object>control</Object>
<Type>scalar</Type>
<IOProtocol>s_axi</IOProtocol>
<Dir>out</Dir>
<Bits>2</Bits>
<Attribute>unknown</Attribute>
<CType>int</CType>
<HasCtrl>1</HasCtrl>
</RtlPorts>
<RtlPorts>
<name>s_axi_control_BVALID</name>
<Object>control</Object>
<Type>scalar</Type>
<IOProtocol>s_axi</IOProtocol>
<Dir>out</Dir>
<Bits>1</Bits>
<Attribute>unknown</Attribute>
<CType>int</CType>
<HasCtrl>1</HasCtrl>
</RtlPorts>
<RtlPorts>
<name>s_axi_control_BREADY</name>
<Object>control</Object>
<Type>scalar</Type>
<IOProtocol>s_axi</IOProtocol>
<Dir>in</Dir>
<Bits>1</Bits>
<Attribute>unknown</Attribute>
<CType>int</CType>
<HasCtrl>1</HasCtrl>
</RtlPorts>
<RtlPorts>
<name>s_axi_control_BRESP</name>
<Object>control</Object>
<Type>scalar</Type>
<IOProtocol>s_axi</IOProtocol>
<Dir>out</Dir>
<Bits>2</Bits>
<Attribute>unknown</Attribute>
<CType>int</CType>
<HasCtrl>1</HasCtrl>
</RtlPorts>
<RtlPorts>
<name>ap_clk</name>
<Object>upconv_core_top_ucb3</Object>
<Type>return value</Type>
<Scope></Scope>
<IOProtocol>ap_ctrl_hs</IOProtocol>
<IOConfig></IOConfig>
<Dir>in</Dir>
<Bits>1</Bits>
<Attribute>control</Attribute>
</RtlPorts>
<RtlPorts>
<name>ap_rst_n</name>
<Object>upconv_core_top_ucb3</Object>
<Type>return value</Type>
<Scope></Scope>
<IOProtocol>ap_ctrl_hs</IOProtocol>
<IOConfig></IOConfig>
<Dir>in</Dir>
<Bits>1</Bits>
<Attribute>control</Attribute>
</RtlPorts>
<RtlPorts>
<name>interrupt</name>
<Object>upconv_core_top_ucb3</Object>
<Type>return value</Type>
<Scope></Scope>
<IOProtocol>ap_ctrl_hs</IOProtocol>
<IOConfig></IOConfig>
<Dir>out</Dir>
<Bits>1</Bits>
<Attribute>unknown</Attribute>
</RtlPorts>
<RtlPorts>
<name>m_axi_gmem_in_AWVALID</name>
<Object>gmem_in</Object>
<Type>pointer</Type>
<Scope></Scope>
<IOProtocol>m_axi</IOProtocol>
<IOConfig></IOConfig>
<Dir>out</Dir>
<Bits>1</Bits>
<Attribute>unknown</Attribute>
<CType>int</CType>
</RtlPorts>
<RtlPorts>
<name>m_axi_gmem_in_AWREADY</name>
<Object>gmem_in</Object>
<Type>pointer</Type>
<Scope></Scope>
<IOProtocol>m_axi</IOProtocol>
<IOConfig></IOConfig>
<Dir>in</Dir>
<Bits>1</Bits>
<Attribute>unknown</Attribute>
<CType>int</CType>
</RtlPorts>
<RtlPorts>
<name>m_axi_gmem_in_AWADDR</name>
<Object>gmem_in</Object>
<Type>pointer</Type>
<Scope></Scope>
<IOProtocol>m_axi</IOProtocol>
<IOConfig></IOConfig>
<Dir>out</Dir>
<Bits>64</Bits>
<Attribute>unknown</Attribute>
<CType>int</CType>
</RtlPorts>
<RtlPorts>
<name>m_axi_gmem_in_AWID</name>
<Object>gmem_in</Object>
<Type>pointer</Type>
<Scope></Scope>
<IOProtocol>m_axi</IOProtocol>
<IOConfig></IOConfig>
<Dir>out</Dir>
<Bits>1</Bits>
<Attribute>unknown</Attribute>
<CType>int</CType>
</RtlPorts>
<RtlPorts>
<name>m_axi_gmem_in_AWLEN</name>
<Object>gmem_in</Object>
<Type>pointer</Type>
<Scope></Scope>
<IOProtocol>m_axi</IOProtocol>
<IOConfig></IOConfig>
<Dir>out</Dir>
<Bits>8</Bits>
<Attribute>unknown</Attribute>
<CType>int</CType>
</RtlPorts>
<RtlPorts>
<name>m_axi_gmem_in_AWSIZE</name>
<Object>gmem_in</Object>
<Type>pointer</Type>
<Scope></Scope>
<IOProtocol>m_axi</IOProtocol>
<IOConfig></IOConfig>
<Dir>out</Dir>
<Bits>3</Bits>
<Attribute>unknown</Attribute>
<CType>int</CType>
</RtlPorts>
<RtlPorts>
<name>m_axi_gmem_in_AWBURST</name>
<Object>gmem_in</Object>
<Type>pointer</Type>
<Scope></Scope>
<IOProtocol>m_axi</IOProtocol>
<IOConfig></IOConfig>
<Dir>out</Dir>
<Bits>2</Bits>
<Attribute>unknown</Attribute>
<CType>int</CType>
</RtlPorts>
<RtlPorts>
<name>m_axi_gmem_in_AWLOCK</name>
<Object>gmem_in</Object>
<Type>pointer</Type>
<Scope></Scope>
<IOProtocol>m_axi</IOProtocol>
<IOConfig></IOConfig>
<Dir>out</Dir>
<Bits>2</Bits>
<Attribute>unknown</Attribute>
<CType>int</CType>
</RtlPorts>
<RtlPorts>
<name>m_axi_gmem_in_AWCACHE</name>
<Object>gmem_in</Object>
<Type>pointer</Type>
<Scope></Scope>
<IOProtocol>m_axi</IOProtocol>
<IOConfig></IOConfig>
<Dir>out</Dir>
<Bits>4</Bits>
<Attribute>unknown</Attribute>
<CType>int</CType>
</RtlPorts>
<RtlPorts>
<name>m_axi_gmem_in_AWPROT</name>
<Object>gmem_in</Object>
<Type>pointer</Type>
<Scope></Scope>
<IOProtocol>m_axi</IOProtocol>
<IOConfig></IOConfig>
<Dir>out</Dir>
<Bits>3</Bits>
<Attribute>unknown</Attribute>
<CType>int</CType>
</RtlPorts>
<RtlPorts>
<name>m_axi_gmem_in_AWQOS</name>
<Object>gmem_in</Object>
<Type>pointer</Type>
<Scope></Scope>
<IOProtocol>m_axi</IOProtocol>
<IOConfig></IOConfig>
<Dir>out</Dir>
<Bits>4</Bits>
<Attribute>unknown</Attribute>
<CType>int</CType>
</RtlPorts>
<RtlPorts>
<name>m_axi_gmem_in_AWREGION</name>
<Object>gmem_in</Object>
<Type>pointer</Type>
<Scope></Scope>
<IOProtocol>m_axi</IOProtocol>
<IOConfig></IOConfig>
<Dir>out</Dir>
<Bits>4</Bits>
<Attribute>unknown</Attribute>
<CType>int</CType>
</RtlPorts>
<RtlPorts>
<name>m_axi_gmem_in_AWUSER</name>
<Object>gmem_in</Object>
<Type>pointer</Type>
<Scope></Scope>
<IOProtocol>m_axi</IOProtocol>
<IOConfig></IOConfig>
<Dir>out</Dir>
<Bits>1</Bits>
<Attribute>unknown</Attribute>
<CType>int</CType>
</RtlPorts>
<RtlPorts>
<name>m_axi_gmem_in_WVALID</name>
<Object>gmem_in</Object>
<Type>pointer</Type>
<Scope></Scope>
<IOProtocol>m_axi</IOProtocol>
<IOConfig></IOConfig>
<Dir>out</Dir>
<Bits>1</Bits>
<Attribute>unknown</Attribute>
<CType>int</CType>
</RtlPorts>
<RtlPorts>
<name>m_axi_gmem_in_WREADY</name>
<Object>gmem_in</Object>
<Type>pointer</Type>
<Scope></Scope>
<IOProtocol>m_axi</IOProtocol>
<IOConfig></IOConfig>
<Dir>in</Dir>
<Bits>1</Bits>
<Attribute>unknown</Attribute>
<CType>int</CType>
</RtlPorts>
<RtlPorts>
<name>m_axi_gmem_in_WDATA</name>
<Object>gmem_in</Object>
<Type>pointer</Type>
<Scope></Scope>
<IOProtocol>m_axi</IOProtocol>
<IOConfig></IOConfig>
<Dir>out</Dir>
<Bits>256</Bits>
<Attribute>unknown</Attribute>
<CType>int</CType>
</RtlPorts>
<RtlPorts>
<name>m_axi_gmem_in_WSTRB</name>
<Object>gmem_in</Object>
<Type>pointer</Type>
<Scope></Scope>
<IOProtocol>m_axi</IOProtocol>
<IOConfig></IOConfig>
<Dir>out</Dir>
<Bits>32</Bits>
<Attribute>unknown</Attribute>
<CType>int</CType>
</RtlPorts>
<RtlPorts>
<name>m_axi_gmem_in_WLAST</name>
<Object>gmem_in</Object>
<Type>pointer</Type>
<Scope></Scope>
<IOProtocol>m_axi</IOProtocol>
<IOConfig></IOConfig>
<Dir>out</Dir>
<Bits>1</Bits>
<Attribute>unknown</Attribute>
<CType>int</CType>
</RtlPorts>
<RtlPorts>
<name>m_axi_gmem_in_WID</name>
<Object>gmem_in</Object>
<Type>pointer</Type>
<Scope></Scope>
<IOProtocol>m_axi</IOProtocol>
<IOConfig></IOConfig>
<Dir>out</Dir>
<Bits>1</Bits>
<Attribute>unknown</Attribute>
<CType>int</CType>
</RtlPorts>
<RtlPorts>
<name>m_axi_gmem_in_WUSER</name>
<Object>gmem_in</Object>
<Type>pointer</Type>
<Scope></Scope>
<IOProtocol>m_axi</IOProtocol>
<IOConfig></IOConfig>
<Dir>out</Dir>
<Bits>1</Bits>
<Attribute>unknown</Attribute>
<CType>int</CType>
</RtlPorts>
<RtlPorts>
<name>m_axi_gmem_in_ARVALID</name>
<Object>gmem_in</Object>
<Type>pointer</Type>
<Scope></Scope>
<IOProtocol>m_axi</IOProtocol>
<IOConfig></IOConfig>
<Dir>out</Dir>
<Bits>1</Bits>
<Attribute>unknown</Attribute>
<CType>int</CType>
</RtlPorts>
<RtlPorts>
<name>m_axi_gmem_in_ARREADY</name>
<Object>gmem_in</Object>
<Type>pointer</Type>
<Scope></Scope>
<IOProtocol>m_axi</IOProtocol>
<IOConfig></IOConfig>
<Dir>in</Dir>
<Bits>1</Bits>
<Attribute>unknown</Attribute>
<CType>int</CType>
</RtlPorts>
<RtlPorts>
<name>m_axi_gmem_in_ARADDR</name>
<Object>gmem_in</Object>
<Type>pointer</Type>
<Scope></Scope>
<IOProtocol>m_axi</IOProtocol>
<IOConfig></IOConfig>
<Dir>out</Dir>
<Bits>64</Bits>
<Attribute>unknown</Attribute>
<CType>int</CType>
</RtlPorts>
<RtlPorts>
<name>m_axi_gmem_in_ARID</name>
<Object>gmem_in</Object>
<Type>pointer</Type>
<Scope></Scope>
<IOProtocol>m_axi</IOProtocol>
<IOConfig></IOConfig>
<Dir>out</Dir>
<Bits>1</Bits>
<Attribute>unknown</Attribute>
<CType>int</CType>
</RtlPorts>
<RtlPorts>
<name>m_axi_gmem_in_ARLEN</name>
<Object>gmem_in</Object>
<Type>pointer</Type>
<Scope></Scope>
<IOProtocol>m_axi</IOProtocol>
<IOConfig></IOConfig>
<Dir>out</Dir>
<Bits>8</Bits>
<Attribute>unknown</Attribute>
<CType>int</CType>
</RtlPorts>
<RtlPorts>
<name>m_axi_gmem_in_ARSIZE</name>
<Object>gmem_in</Object>
<Type>pointer</Type>
<Scope></Scope>
<IOProtocol>m_axi</IOProtocol>
<IOConfig></IOConfig>
<Dir>out</Dir>
<Bits>3</Bits>
<Attribute>unknown</Attribute>
<CType>int</CType>
</RtlPorts>
<RtlPorts>
<name>m_axi_gmem_in_ARBURST</name>
<Object>gmem_in</Object>
<Type>pointer</Type>
<Scope></Scope>
<IOProtocol>m_axi</IOProtocol>
<IOConfig></IOConfig>
<Dir>out</Dir>
<Bits>2</Bits>
<Attribute>unknown</Attribute>
<CType>int</CType>
</RtlPorts>
<RtlPorts>
<name>m_axi_gmem_in_ARLOCK</name>
<Object>gmem_in</Object>
<Type>pointer</Type>
<Scope></Scope>
<IOProtocol>m_axi</IOProtocol>
<IOConfig></IOConfig>
<Dir>out</Dir>
<Bits>2</Bits>
<Attribute>unknown</Attribute>
<CType>int</CType>
</RtlPorts>
<RtlPorts>
<name>m_axi_gmem_in_ARCACHE</name>
<Object>gmem_in</Object>
<Type>pointer</Type>
<Scope></Scope>
<IOProtocol>m_axi</IOProtocol>
<IOConfig></IOConfig>
<Dir>out</Dir>
<Bits>4</Bits>
<Attribute>unknown</Attribute>
<CType>int</CType>
</RtlPorts>
<RtlPorts>
<name>m_axi_gmem_in_ARPROT</name>
<Object>gmem_in</Object>
<Type>pointer</Type>
<Scope></Scope>
<IOProtocol>m_axi</IOProtocol>
<IOConfig></IOConfig>
<Dir>out</Dir>
<Bits>3</Bits>
<Attribute>unknown</Attribute>
<CType>int</CType>
</RtlPorts>
<RtlPorts>
<name>m_axi_gmem_in_ARQOS</name>
<Object>gmem_in</Object>
<Type>pointer</Type>
<Scope></Scope>
<IOProtocol>m_axi</IOProtocol>
<IOConfig></IOConfig>
<Dir>out</Dir>
<Bits>4</Bits>
<Attribute>unknown</Attribute>
<CType>int</CType>
</RtlPorts>
<RtlPorts>
<name>m_axi_gmem_in_ARREGION</name>
<Object>gmem_in</Object>
<Type>pointer</Type>
<Scope></Scope>
<IOProtocol>m_axi</IOProtocol>
<IOConfig></IOConfig>
<Dir>out</Dir>
<Bits>4</Bits>
<Attribute>unknown</Attribute>
<CType>int</CType>
</RtlPorts>
<RtlPorts>
<name>m_axi_gmem_in_ARUSER</name>
<Object>gmem_in</Object>
<Type>pointer</Type>
<Scope></Scope>
<IOProtocol>m_axi</IOProtocol>
<IOConfig></IOConfig>
<Dir>out</Dir>
<Bits>1</Bits>
<Attribute>unknown</Attribute>
<CType>int</CType>
</RtlPorts>
<RtlPorts>
<name>m_axi_gmem_in_RVALID</name>
<Object>gmem_in</Object>
<Type>pointer</Type>
<Scope></Scope>
<IOProtocol>m_axi</IOProtocol>
<IOConfig></IOConfig>
<Dir>in</Dir>
<Bits>1</Bits>
<Attribute>unknown</Attribute>
<CType>int</CType>
</RtlPorts>
<RtlPorts>
<name>m_axi_gmem_in_RREADY</name>
<Object>gmem_in</Object>
<Type>pointer</Type>
<Scope></Scope>
<IOProtocol>m_axi</IOProtocol>
<IOConfig></IOConfig>
<Dir>out</Dir>
<Bits>1</Bits>
<Attribute>unknown</Attribute>
<CType>int</CType>
</RtlPorts>
<RtlPorts>
<name>m_axi_gmem_in_RDATA</name>
<Object>gmem_in</Object>
<Type>pointer</Type>
<Scope></Scope>
<IOProtocol>m_axi</IOProtocol>
<IOConfig></IOConfig>
<Dir>in</Dir>
<Bits>256</Bits>
<Attribute>unknown</Attribute>
<CType>int</CType>
</RtlPorts>
<RtlPorts>
<name>m_axi_gmem_in_RLAST</name>
<Object>gmem_in</Object>
<Type>pointer</Type>
<Scope></Scope>
<IOProtocol>m_axi</IOProtocol>
<IOConfig></IOConfig>
<Dir>in</Dir>
<Bits>1</Bits>
<Attribute>unknown</Attribute>
<CType>int</CType>
</RtlPorts>
<RtlPorts>
<name>m_axi_gmem_in_RID</name>
<Object>gmem_in</Object>
<Type>pointer</Type>
<Scope></Scope>
<IOProtocol>m_axi</IOProtocol>
<IOConfig></IOConfig>
<Dir>in</Dir>
<Bits>1</Bits>
<Attribute>unknown</Attribute>
<CType>int</CType>
</RtlPorts>
<RtlPorts>
<name>m_axi_gmem_in_RUSER</name>
<Object>gmem_in</Object>
<Type>pointer</Type>
<Scope></Scope>
<IOProtocol>m_axi</IOProtocol>
<IOConfig></IOConfig>
<Dir>in</Dir>
<Bits>1</Bits>
<Attribute>unknown</Attribute>
<CType>int</CType>
</RtlPorts>
<RtlPorts>
<name>m_axi_gmem_in_RRESP</name>
<Object>gmem_in</Object>
<Type>pointer</Type>
<Scope></Scope>
<IOProtocol>m_axi</IOProtocol>
<IOConfig></IOConfig>
<Dir>in</Dir>
<Bits>2</Bits>
<Attribute>unknown</Attribute>
<CType>int</CType>
</RtlPorts>
<RtlPorts>
<name>m_axi_gmem_in_BVALID</name>
<Object>gmem_in</Object>
<Type>pointer</Type>
<Scope></Scope>
<IOProtocol>m_axi</IOProtocol>
<IOConfig></IOConfig>
<Dir>in</Dir>
<Bits>1</Bits>
<Attribute>unknown</Attribute>
<CType>int</CType>
</RtlPorts>
<RtlPorts>
<name>m_axi_gmem_in_BREADY</name>
<Object>gmem_in</Object>
<Type>pointer</Type>
<Scope></Scope>
<IOProtocol>m_axi</IOProtocol>
<IOConfig></IOConfig>
<Dir>out</Dir>
<Bits>1</Bits>
<Attribute>unknown</Attribute>
<CType>int</CType>
</RtlPorts>
<RtlPorts>
<name>m_axi_gmem_in_BRESP</name>
<Object>gmem_in</Object>
<Type>pointer</Type>
<Scope></Scope>
<IOProtocol>m_axi</IOProtocol>
<IOConfig></IOConfig>
<Dir>in</Dir>
<Bits>2</Bits>
<Attribute>unknown</Attribute>
<CType>int</CType>
</RtlPorts>
<RtlPorts>
<name>m_axi_gmem_in_BID</name>
<Object>gmem_in</Object>
<Type>pointer</Type>
<Scope></Scope>
<IOProtocol>m_axi</IOProtocol>
<IOConfig></IOConfig>
<Dir>in</Dir>
<Bits>1</Bits>
<Attribute>unknown</Attribute>
<CType>int</CType>
</RtlPorts>
<RtlPorts>
<name>m_axi_gmem_in_BUSER</name>
<Object>gmem_in</Object>
<Type>pointer</Type>
<Scope></Scope>
<IOProtocol>m_axi</IOProtocol>
<IOConfig></IOConfig>
<Dir>in</Dir>
<Bits>1</Bits>
<Attribute>unknown</Attribute>
<CType>int</CType>
</RtlPorts>
<RtlPorts>
<name>m_axi_gmem_weight_AWVALID</name>
<Object>gmem_weight</Object>
<Type>pointer</Type>
<Scope></Scope>
<IOProtocol>m_axi</IOProtocol>
<IOConfig></IOConfig>
<Dir>out</Dir>
<Bits>1</Bits>
<Attribute>unknown</Attribute>
<CType>int</CType>
</RtlPorts>
<RtlPorts>
<name>m_axi_gmem_weight_AWREADY</name>
<Object>gmem_weight</Object>
<Type>pointer</Type>
<Scope></Scope>
<IOProtocol>m_axi</IOProtocol>
<IOConfig></IOConfig>
<Dir>in</Dir>
<Bits>1</Bits>
<Attribute>unknown</Attribute>
<CType>int</CType>
</RtlPorts>
<RtlPorts>
<name>m_axi_gmem_weight_AWADDR</name>
<Object>gmem_weight</Object>
<Type>pointer</Type>
<Scope></Scope>
<IOProtocol>m_axi</IOProtocol>
<IOConfig></IOConfig>
<Dir>out</Dir>
<Bits>64</Bits>
<Attribute>unknown</Attribute>
<CType>int</CType>
</RtlPorts>
<RtlPorts>
<name>m_axi_gmem_weight_AWID</name>
<Object>gmem_weight</Object>
<Type>pointer</Type>
<Scope></Scope>
<IOProtocol>m_axi</IOProtocol>
<IOConfig></IOConfig>
<Dir>out</Dir>
<Bits>1</Bits>
<Attribute>unknown</Attribute>
<CType>int</CType>
</RtlPorts>
<RtlPorts>
<name>m_axi_gmem_weight_AWLEN</name>
<Object>gmem_weight</Object>
<Type>pointer</Type>
<Scope></Scope>
<IOProtocol>m_axi</IOProtocol>
<IOConfig></IOConfig>
<Dir>out</Dir>
<Bits>8</Bits>
<Attribute>unknown</Attribute>
<CType>int</CType>
</RtlPorts>
<RtlPorts>
<name>m_axi_gmem_weight_AWSIZE</name>
<Object>gmem_weight</Object>
<Type>pointer</Type>
<Scope></Scope>
<IOProtocol>m_axi</IOProtocol>
<IOConfig></IOConfig>
<Dir>out</Dir>
<Bits>3</Bits>
<Attribute>unknown</Attribute>
<CType>int</CType>
</RtlPorts>
<RtlPorts>
<name>m_axi_gmem_weight_AWBURST</name>
<Object>gmem_weight</Object>
<Type>pointer</Type>
<Scope></Scope>
<IOProtocol>m_axi</IOProtocol>
<IOConfig></IOConfig>
<Dir>out</Dir>
<Bits>2</Bits>
<Attribute>unknown</Attribute>
<CType>int</CType>
</RtlPorts>
<RtlPorts>
<name>m_axi_gmem_weight_AWLOCK</name>
<Object>gmem_weight</Object>
<Type>pointer</Type>
<Scope></Scope>
<IOProtocol>m_axi</IOProtocol>
<IOConfig></IOConfig>
<Dir>out</Dir>
<Bits>2</Bits>
<Attribute>unknown</Attribute>
<CType>int</CType>
</RtlPorts>
<RtlPorts>
<name>m_axi_gmem_weight_AWCACHE</name>
<Object>gmem_weight</Object>
<Type>pointer</Type>
<Scope></Scope>
<IOProtocol>m_axi</IOProtocol>
<IOConfig></IOConfig>
<Dir>out</Dir>
<Bits>4</Bits>
<Attribute>unknown</Attribute>
<CType>int</CType>
</RtlPorts>
<RtlPorts>
<name>m_axi_gmem_weight_AWPROT</name>
<Object>gmem_weight</Object>
<Type>pointer</Type>
<Scope></Scope>
<IOProtocol>m_axi</IOProtocol>
<IOConfig></IOConfig>
<Dir>out</Dir>
<Bits>3</Bits>
<Attribute>unknown</Attribute>
<CType>int</CType>
</RtlPorts>
<RtlPorts>
<name>m_axi_gmem_weight_AWQOS</name>
<Object>gmem_weight</Object>
<Type>pointer</Type>
<Scope></Scope>
<IOProtocol>m_axi</IOProtocol>
<IOConfig></IOConfig>
<Dir>out</Dir>
<Bits>4</Bits>
<Attribute>unknown</Attribute>
<CType>int</CType>
</RtlPorts>
<RtlPorts>
<name>m_axi_gmem_weight_AWREGION</name>
<Object>gmem_weight</Object>
<Type>pointer</Type>
<Scope></Scope>
<IOProtocol>m_axi</IOProtocol>
<IOConfig></IOConfig>
<Dir>out</Dir>
<Bits>4</Bits>
<Attribute>unknown</Attribute>
<CType>int</CType>
</RtlPorts>
<RtlPorts>
<name>m_axi_gmem_weight_AWUSER</name>
<Object>gmem_weight</Object>
<Type>pointer</Type>
<Scope></Scope>
<IOProtocol>m_axi</IOProtocol>
<IOConfig></IOConfig>
<Dir>out</Dir>
<Bits>1</Bits>
<Attribute>unknown</Attribute>
<CType>int</CType>
</RtlPorts>
<RtlPorts>
<name>m_axi_gmem_weight_WVALID</name>
<Object>gmem_weight</Object>
<Type>pointer</Type>
<Scope></Scope>
<IOProtocol>m_axi</IOProtocol>
<IOConfig></IOConfig>
<Dir>out</Dir>
<Bits>1</Bits>
<Attribute>unknown</Attribute>
<CType>int</CType>
</RtlPorts>
<RtlPorts>
<name>m_axi_gmem_weight_WREADY</name>
<Object>gmem_weight</Object>
<Type>pointer</Type>
<Scope></Scope>
<IOProtocol>m_axi</IOProtocol>
<IOConfig></IOConfig>
<Dir>in</Dir>
<Bits>1</Bits>
<Attribute>unknown</Attribute>
<CType>int</CType>
</RtlPorts>
<RtlPorts>
<name>m_axi_gmem_weight_WDATA</name>
<Object>gmem_weight</Object>
<Type>pointer</Type>
<Scope></Scope>
<IOProtocol>m_axi</IOProtocol>
<IOConfig></IOConfig>
<Dir>out</Dir>
<Bits>256</Bits>
<Attribute>unknown</Attribute>
<CType>int</CType>
</RtlPorts>
<RtlPorts>
<name>m_axi_gmem_weight_WSTRB</name>
<Object>gmem_weight</Object>
<Type>pointer</Type>
<Scope></Scope>
<IOProtocol>m_axi</IOProtocol>
<IOConfig></IOConfig>
<Dir>out</Dir>
<Bits>32</Bits>
<Attribute>unknown</Attribute>
<CType>int</CType>
</RtlPorts>
<RtlPorts>
<name>m_axi_gmem_weight_WLAST</name>
<Object>gmem_weight</Object>
<Type>pointer</Type>
<Scope></Scope>
<IOProtocol>m_axi</IOProtocol>
<IOConfig></IOConfig>
<Dir>out</Dir>
<Bits>1</Bits>
<Attribute>unknown</Attribute>
<CType>int</CType>
</RtlPorts>
<RtlPorts>
<name>m_axi_gmem_weight_WID</name>
<Object>gmem_weight</Object>
<Type>pointer</Type>
<Scope></Scope>
<IOProtocol>m_axi</IOProtocol>
<IOConfig></IOConfig>
<Dir>out</Dir>
<Bits>1</Bits>
<Attribute>unknown</Attribute>
<CType>int</CType>
</RtlPorts>
<RtlPorts>
<name>m_axi_gmem_weight_WUSER</name>
<Object>gmem_weight</Object>
<Type>pointer</Type>
<Scope></Scope>
<IOProtocol>m_axi</IOProtocol>
<IOConfig></IOConfig>
<Dir>out</Dir>
<Bits>1</Bits>
<Attribute>unknown</Attribute>
<CType>int</CType>
</RtlPorts>
<RtlPorts>
<name>m_axi_gmem_weight_ARVALID</name>
<Object>gmem_weight</Object>
<Type>pointer</Type>
<Scope></Scope>
<IOProtocol>m_axi</IOProtocol>
<IOConfig></IOConfig>
<Dir>out</Dir>
<Bits>1</Bits>
<Attribute>unknown</Attribute>
<CType>int</CType>
</RtlPorts>
<RtlPorts>
<name>m_axi_gmem_weight_ARREADY</name>
<Object>gmem_weight</Object>
<Type>pointer</Type>
<Scope></Scope>
<IOProtocol>m_axi</IOProtocol>
<IOConfig></IOConfig>
<Dir>in</Dir>
<Bits>1</Bits>
<Attribute>unknown</Attribute>
<CType>int</CType>
</RtlPorts>
<RtlPorts>
<name>m_axi_gmem_weight_ARADDR</name>
<Object>gmem_weight</Object>
<Type>pointer</Type>
<Scope></Scope>
<IOProtocol>m_axi</IOProtocol>
<IOConfig></IOConfig>
<Dir>out</Dir>
<Bits>64</Bits>
<Attribute>unknown</Attribute>
<CType>int</CType>
</RtlPorts>
<RtlPorts>
<name>m_axi_gmem_weight_ARID</name>
<Object>gmem_weight</Object>
<Type>pointer</Type>
<Scope></Scope>
<IOProtocol>m_axi</IOProtocol>
<IOConfig></IOConfig>
<Dir>out</Dir>
<Bits>1</Bits>
<Attribute>unknown</Attribute>
<CType>int</CType>
</RtlPorts>
<RtlPorts>
<name>m_axi_gmem_weight_ARLEN</name>
<Object>gmem_weight</Object>
<Type>pointer</Type>
<Scope></Scope>
<IOProtocol>m_axi</IOProtocol>
<IOConfig></IOConfig>
<Dir>out</Dir>
<Bits>8</Bits>
<Attribute>unknown</Attribute>
<CType>int</CType>
</RtlPorts>
<RtlPorts>
<name>m_axi_gmem_weight_ARSIZE</name>
<Object>gmem_weight</Object>
<Type>pointer</Type>
<Scope></Scope>
<IOProtocol>m_axi</IOProtocol>
<IOConfig></IOConfig>
<Dir>out</Dir>
<Bits>3</Bits>
<Attribute>unknown</Attribute>
<CType>int</CType>
</RtlPorts>
<RtlPorts>
<name>m_axi_gmem_weight_ARBURST</name>
<Object>gmem_weight</Object>
<Type>pointer</Type>
<Scope></Scope>
<IOProtocol>m_axi</IOProtocol>
<IOConfig></IOConfig>
<Dir>out</Dir>
<Bits>2</Bits>
<Attribute>unknown</Attribute>
<CType>int</CType>
</RtlPorts>
<RtlPorts>
<name>m_axi_gmem_weight_ARLOCK</name>
<Object>gmem_weight</Object>
<Type>pointer</Type>
<Scope></Scope>
<IOProtocol>m_axi</IOProtocol>
<IOConfig></IOConfig>
<Dir>out</Dir>
<Bits>2</Bits>
<Attribute>unknown</Attribute>
<CType>int</CType>
</RtlPorts>
<RtlPorts>
<name>m_axi_gmem_weight_ARCACHE</name>
<Object>gmem_weight</Object>
<Type>pointer</Type>
<Scope></Scope>
<IOProtocol>m_axi</IOProtocol>
<IOConfig></IOConfig>
<Dir>out</Dir>
<Bits>4</Bits>
<Attribute>unknown</Attribute>
<CType>int</CType>
</RtlPorts>
<RtlPorts>
<name>m_axi_gmem_weight_ARPROT</name>
<Object>gmem_weight</Object>
<Type>pointer</Type>
<Scope></Scope>
<IOProtocol>m_axi</IOProtocol>
<IOConfig></IOConfig>
<Dir>out</Dir>
<Bits>3</Bits>
<Attribute>unknown</Attribute>
<CType>int</CType>
</RtlPorts>
<RtlPorts>
<name>m_axi_gmem_weight_ARQOS</name>
<Object>gmem_weight</Object>
<Type>pointer</Type>
<Scope></Scope>
<IOProtocol>m_axi</IOProtocol>
<IOConfig></IOConfig>
<Dir>out</Dir>
<Bits>4</Bits>
<Attribute>unknown</Attribute>
<CType>int</CType>
</RtlPorts>
<RtlPorts>
<name>m_axi_gmem_weight_ARREGION</name>
<Object>gmem_weight</Object>
<Type>pointer</Type>
<Scope></Scope>
<IOProtocol>m_axi</IOProtocol>
<IOConfig></IOConfig>
<Dir>out</Dir>
<Bits>4</Bits>
<Attribute>unknown</Attribute>
<CType>int</CType>
</RtlPorts>
<RtlPorts>
<name>m_axi_gmem_weight_ARUSER</name>
<Object>gmem_weight</Object>
<Type>pointer</Type>
<Scope></Scope>
<IOProtocol>m_axi</IOProtocol>
<IOConfig></IOConfig>
<Dir>out</Dir>
<Bits>1</Bits>
<Attribute>unknown</Attribute>
<CType>int</CType>
</RtlPorts>
<RtlPorts>
<name>m_axi_gmem_weight_RVALID</name>
<Object>gmem_weight</Object>
<Type>pointer</Type>
<Scope></Scope>
<IOProtocol>m_axi</IOProtocol>
<IOConfig></IOConfig>
<Dir>in</Dir>
<Bits>1</Bits>
<Attribute>unknown</Attribute>
<CType>int</CType>
</RtlPorts>
<RtlPorts>
<name>m_axi_gmem_weight_RREADY</name>
<Object>gmem_weight</Object>
<Type>pointer</Type>
<Scope></Scope>
<IOProtocol>m_axi</IOProtocol>
<IOConfig></IOConfig>
<Dir>out</Dir>
<Bits>1</Bits>
<Attribute>unknown</Attribute>
<CType>int</CType>
</RtlPorts>
<RtlPorts>
<name>m_axi_gmem_weight_RDATA</name>
<Object>gmem_weight</Object>
<Type>pointer</Type>
<Scope></Scope>
<IOProtocol>m_axi</IOProtocol>
<IOConfig></IOConfig>
<Dir>in</Dir>
<Bits>256</Bits>
<Attribute>unknown</Attribute>
<CType>int</CType>
</RtlPorts>
<RtlPorts>
<name>m_axi_gmem_weight_RLAST</name>
<Object>gmem_weight</Object>
<Type>pointer</Type>
<Scope></Scope>
<IOProtocol>m_axi</IOProtocol>
<IOConfig></IOConfig>
<Dir>in</Dir>
<Bits>1</Bits>
<Attribute>unknown</Attribute>
<CType>int</CType>
</RtlPorts>
<RtlPorts>
<name>m_axi_gmem_weight_RID</name>
<Object>gmem_weight</Object>
<Type>pointer</Type>
<Scope></Scope>
<IOProtocol>m_axi</IOProtocol>
<IOConfig></IOConfig>
<Dir>in</Dir>
<Bits>1</Bits>
<Attribute>unknown</Attribute>
<CType>int</CType>
</RtlPorts>
<RtlPorts>
<name>m_axi_gmem_weight_RUSER</name>
<Object>gmem_weight</Object>
<Type>pointer</Type>
<Scope></Scope>
<IOProtocol>m_axi</IOProtocol>
<IOConfig></IOConfig>
<Dir>in</Dir>
<Bits>1</Bits>
<Attribute>unknown</Attribute>
<CType>int</CType>
</RtlPorts>
<RtlPorts>
<name>m_axi_gmem_weight_RRESP</name>
<Object>gmem_weight</Object>
<Type>pointer</Type>
<Scope></Scope>
<IOProtocol>m_axi</IOProtocol>
<IOConfig></IOConfig>
<Dir>in</Dir>
<Bits>2</Bits>
<Attribute>unknown</Attribute>
<CType>int</CType>
</RtlPorts>
<RtlPorts>
<name>m_axi_gmem_weight_BVALID</name>
<Object>gmem_weight</Object>
<Type>pointer</Type>
<Scope></Scope>
<IOProtocol>m_axi</IOProtocol>
<IOConfig></IOConfig>
<Dir>in</Dir>
<Bits>1</Bits>
<Attribute>unknown</Attribute>
<CType>int</CType>
</RtlPorts>
<RtlPorts>
<name>m_axi_gmem_weight_BREADY</name>
<Object>gmem_weight</Object>
<Type>pointer</Type>
<Scope></Scope>
<IOProtocol>m_axi</IOProtocol>
<IOConfig></IOConfig>
<Dir>out</Dir>
<Bits>1</Bits>
<Attribute>unknown</Attribute>
<CType>int</CType>
</RtlPorts>
<RtlPorts>
<name>m_axi_gmem_weight_BRESP</name>
<Object>gmem_weight</Object>
<Type>pointer</Type>
<Scope></Scope>
<IOProtocol>m_axi</IOProtocol>
<IOConfig></IOConfig>
<Dir>in</Dir>
<Bits>2</Bits>
<Attribute>unknown</Attribute>
<CType>int</CType>
</RtlPorts>
<RtlPorts>
<name>m_axi_gmem_weight_BID</name>
<Object>gmem_weight</Object>
<Type>pointer</Type>
<Scope></Scope>
<IOProtocol>m_axi</IOProtocol>
<IOConfig></IOConfig>
<Dir>in</Dir>
<Bits>1</Bits>
<Attribute>unknown</Attribute>
<CType>int</CType>
</RtlPorts>
<RtlPorts>
<name>m_axi_gmem_weight_BUSER</name>
<Object>gmem_weight</Object>
<Type>pointer</Type>
<Scope></Scope>
<IOProtocol>m_axi</IOProtocol>
<IOConfig></IOConfig>
<Dir>in</Dir>
<Bits>1</Bits>
<Attribute>unknown</Attribute>
<CType>int</CType>
</RtlPorts>
<RtlPorts>
<name>m_axi_gmem_param_AWVALID</name>
<Object>gmem_param</Object>
<Type>pointer</Type>
<Scope></Scope>
<IOProtocol>m_axi</IOProtocol>
<IOConfig></IOConfig>
<Dir>out</Dir>
<Bits>1</Bits>
<Attribute>unknown</Attribute>
<CType>int</CType>
</RtlPorts>
<RtlPorts>
<name>m_axi_gmem_param_AWREADY</name>
<Object>gmem_param</Object>
<Type>pointer</Type>
<Scope></Scope>
<IOProtocol>m_axi</IOProtocol>
<IOConfig></IOConfig>
<Dir>in</Dir>
<Bits>1</Bits>
<Attribute>unknown</Attribute>
<CType>int</CType>
</RtlPorts>
<RtlPorts>
<name>m_axi_gmem_param_AWADDR</name>
<Object>gmem_param</Object>
<Type>pointer</Type>
<Scope></Scope>
<IOProtocol>m_axi</IOProtocol>
<IOConfig></IOConfig>
<Dir>out</Dir>
<Bits>64</Bits>
<Attribute>unknown</Attribute>
<CType>int</CType>
</RtlPorts>
<RtlPorts>
<name>m_axi_gmem_param_AWID</name>
<Object>gmem_param</Object>
<Type>pointer</Type>
<Scope></Scope>
<IOProtocol>m_axi</IOProtocol>
<IOConfig></IOConfig>
<Dir>out</Dir>
<Bits>1</Bits>
<Attribute>unknown</Attribute>
<CType>int</CType>
</RtlPorts>
<RtlPorts>
<name>m_axi_gmem_param_AWLEN</name>
<Object>gmem_param</Object>
<Type>pointer</Type>
<Scope></Scope>
<IOProtocol>m_axi</IOProtocol>
<IOConfig></IOConfig>
<Dir>out</Dir>
<Bits>8</Bits>
<Attribute>unknown</Attribute>
<CType>int</CType>
</RtlPorts>
<RtlPorts>
<name>m_axi_gmem_param_AWSIZE</name>
<Object>gmem_param</Object>
<Type>pointer</Type>
<Scope></Scope>
<IOProtocol>m_axi</IOProtocol>
<IOConfig></IOConfig>
<Dir>out</Dir>
<Bits>3</Bits>
<Attribute>unknown</Attribute>
<CType>int</CType>
</RtlPorts>
<RtlPorts>
<name>m_axi_gmem_param_AWBURST</name>
<Object>gmem_param</Object>
<Type>pointer</Type>
<Scope></Scope>
<IOProtocol>m_axi</IOProtocol>
<IOConfig></IOConfig>
<Dir>out</Dir>
<Bits>2</Bits>
<Attribute>unknown</Attribute>
<CType>int</CType>
</RtlPorts>
<RtlPorts>
<name>m_axi_gmem_param_AWLOCK</name>
<Object>gmem_param</Object>
<Type>pointer</Type>
<Scope></Scope>
<IOProtocol>m_axi</IOProtocol>
<IOConfig></IOConfig>
<Dir>out</Dir>
<Bits>2</Bits>
<Attribute>unknown</Attribute>
<CType>int</CType>
</RtlPorts>
<RtlPorts>
<name>m_axi_gmem_param_AWCACHE</name>
<Object>gmem_param</Object>
<Type>pointer</Type>
<Scope></Scope>
<IOProtocol>m_axi</IOProtocol>
<IOConfig></IOConfig>
<Dir>out</Dir>
<Bits>4</Bits>
<Attribute>unknown</Attribute>
<CType>int</CType>
</RtlPorts>
<RtlPorts>
<name>m_axi_gmem_param_AWPROT</name>
<Object>gmem_param</Object>
<Type>pointer</Type>
<Scope></Scope>
<IOProtocol>m_axi</IOProtocol>
<IOConfig></IOConfig>
<Dir>out</Dir>
<Bits>3</Bits>
<Attribute>unknown</Attribute>
<CType>int</CType>
</RtlPorts>
<RtlPorts>
<name>m_axi_gmem_param_AWQOS</name>
<Object>gmem_param</Object>
<Type>pointer</Type>
<Scope></Scope>
<IOProtocol>m_axi</IOProtocol>
<IOConfig></IOConfig>
<Dir>out</Dir>
<Bits>4</Bits>
<Attribute>unknown</Attribute>
<CType>int</CType>
</RtlPorts>
<RtlPorts>
<name>m_axi_gmem_param_AWREGION</name>
<Object>gmem_param</Object>
<Type>pointer</Type>
<Scope></Scope>
<IOProtocol>m_axi</IOProtocol>
<IOConfig></IOConfig>
<Dir>out</Dir>
<Bits>4</Bits>
<Attribute>unknown</Attribute>
<CType>int</CType>
</RtlPorts>
<RtlPorts>
<name>m_axi_gmem_param_AWUSER</name>
<Object>gmem_param</Object>
<Type>pointer</Type>
<Scope></Scope>
<IOProtocol>m_axi</IOProtocol>
<IOConfig></IOConfig>
<Dir>out</Dir>
<Bits>1</Bits>
<Attribute>unknown</Attribute>
<CType>int</CType>
</RtlPorts>
<RtlPorts>
<name>m_axi_gmem_param_WVALID</name>
<Object>gmem_param</Object>
<Type>pointer</Type>
<Scope></Scope>
<IOProtocol>m_axi</IOProtocol>
<IOConfig></IOConfig>
<Dir>out</Dir>
<Bits>1</Bits>
<Attribute>unknown</Attribute>
<CType>int</CType>
</RtlPorts>
<RtlPorts>
<name>m_axi_gmem_param_WREADY</name>
<Object>gmem_param</Object>
<Type>pointer</Type>
<Scope></Scope>
<IOProtocol>m_axi</IOProtocol>
<IOConfig></IOConfig>
<Dir>in</Dir>
<Bits>1</Bits>
<Attribute>unknown</Attribute>
<CType>int</CType>
</RtlPorts>
<RtlPorts>
<name>m_axi_gmem_param_WDATA</name>
<Object>gmem_param</Object>
<Type>pointer</Type>
<Scope></Scope>
<IOProtocol>m_axi</IOProtocol>
<IOConfig></IOConfig>
<Dir>out</Dir>
<Bits>256</Bits>
<Attribute>unknown</Attribute>
<CType>int</CType>
</RtlPorts>
<RtlPorts>
<name>m_axi_gmem_param_WSTRB</name>
<Object>gmem_param</Object>
<Type>pointer</Type>
<Scope></Scope>
<IOProtocol>m_axi</IOProtocol>
<IOConfig></IOConfig>
<Dir>out</Dir>
<Bits>32</Bits>
<Attribute>unknown</Attribute>
<CType>int</CType>
</RtlPorts>
<RtlPorts>
<name>m_axi_gmem_param_WLAST</name>
<Object>gmem_param</Object>
<Type>pointer</Type>
<Scope></Scope>
<IOProtocol>m_axi</IOProtocol>
<IOConfig></IOConfig>
<Dir>out</Dir>
<Bits>1</Bits>
<Attribute>unknown</Attribute>
<CType>int</CType>
</RtlPorts>
<RtlPorts>
<name>m_axi_gmem_param_WID</name>
<Object>gmem_param</Object>
<Type>pointer</Type>
<Scope></Scope>
<IOProtocol>m_axi</IOProtocol>
<IOConfig></IOConfig>
<Dir>out</Dir>
<Bits>1</Bits>
<Attribute>unknown</Attribute>
<CType>int</CType>
</RtlPorts>
<RtlPorts>
<name>m_axi_gmem_param_WUSER</name>
<Object>gmem_param</Object>
<Type>pointer</Type>
<Scope></Scope>
<IOProtocol>m_axi</IOProtocol>
<IOConfig></IOConfig>
<Dir>out</Dir>
<Bits>1</Bits>
<Attribute>unknown</Attribute>
<CType>int</CType>
</RtlPorts>
<RtlPorts>
<name>m_axi_gmem_param_ARVALID</name>
<Object>gmem_param</Object>
<Type>pointer</Type>
<Scope></Scope>
<IOProtocol>m_axi</IOProtocol>
<IOConfig></IOConfig>
<Dir>out</Dir>
<Bits>1</Bits>
<Attribute>unknown</Attribute>
<CType>int</CType>
</RtlPorts>
<RtlPorts>
<name>m_axi_gmem_param_ARREADY</name>
<Object>gmem_param</Object>
<Type>pointer</Type>
<Scope></Scope>
<IOProtocol>m_axi</IOProtocol>
<IOConfig></IOConfig>
<Dir>in</Dir>
<Bits>1</Bits>
<Attribute>unknown</Attribute>
<CType>int</CType>
</RtlPorts>
<RtlPorts>
<name>m_axi_gmem_param_ARADDR</name>
<Object>gmem_param</Object>
<Type>pointer</Type>
<Scope></Scope>
<IOProtocol>m_axi</IOProtocol>
<IOConfig></IOConfig>
<Dir>out</Dir>
<Bits>64</Bits>
<Attribute>unknown</Attribute>
<CType>int</CType>
</RtlPorts>
<RtlPorts>
<name>m_axi_gmem_param_ARID</name>
<Object>gmem_param</Object>
<Type>pointer</Type>
<Scope></Scope>
<IOProtocol>m_axi</IOProtocol>
<IOConfig></IOConfig>
<Dir>out</Dir>
<Bits>1</Bits>
<Attribute>unknown</Attribute>
<CType>int</CType>
</RtlPorts>
<RtlPorts>
<name>m_axi_gmem_param_ARLEN</name>
<Object>gmem_param</Object>
<Type>pointer</Type>
<Scope></Scope>
<IOProtocol>m_axi</IOProtocol>
<IOConfig></IOConfig>
<Dir>out</Dir>
<Bits>8</Bits>
<Attribute>unknown</Attribute>
<CType>int</CType>
</RtlPorts>
<RtlPorts>
<name>m_axi_gmem_param_ARSIZE</name>
<Object>gmem_param</Object>
<Type>pointer</Type>
<Scope></Scope>
<IOProtocol>m_axi</IOProtocol>
<IOConfig></IOConfig>
<Dir>out</Dir>
<Bits>3</Bits>
<Attribute>unknown</Attribute>
<CType>int</CType>
</RtlPorts>
<RtlPorts>
<name>m_axi_gmem_param_ARBURST</name>
<Object>gmem_param</Object>
<Type>pointer</Type>
<Scope></Scope>
<IOProtocol>m_axi</IOProtocol>
<IOConfig></IOConfig>
<Dir>out</Dir>
<Bits>2</Bits>
<Attribute>unknown</Attribute>
<CType>int</CType>
</RtlPorts>
<RtlPorts>
<name>m_axi_gmem_param_ARLOCK</name>
<Object>gmem_param</Object>
<Type>pointer</Type>
<Scope></Scope>
<IOProtocol>m_axi</IOProtocol>
<IOConfig></IOConfig>
<Dir>out</Dir>
<Bits>2</Bits>
<Attribute>unknown</Attribute>
<CType>int</CType>
</RtlPorts>
<RtlPorts>
<name>m_axi_gmem_param_ARCACHE</name>
<Object>gmem_param</Object>
<Type>pointer</Type>
<Scope></Scope>
<IOProtocol>m_axi</IOProtocol>
<IOConfig></IOConfig>
<Dir>out</Dir>
<Bits>4</Bits>
<Attribute>unknown</Attribute>
<CType>int</CType>
</RtlPorts>
<RtlPorts>
<name>m_axi_gmem_param_ARPROT</name>
<Object>gmem_param</Object>
<Type>pointer</Type>
<Scope></Scope>
<IOProtocol>m_axi</IOProtocol>
<IOConfig></IOConfig>
<Dir>out</Dir>
<Bits>3</Bits>
<Attribute>unknown</Attribute>
<CType>int</CType>
</RtlPorts>
<RtlPorts>
<name>m_axi_gmem_param_ARQOS</name>
<Object>gmem_param</Object>
<Type>pointer</Type>
<Scope></Scope>
<IOProtocol>m_axi</IOProtocol>
<IOConfig></IOConfig>
<Dir>out</Dir>
<Bits>4</Bits>
<Attribute>unknown</Attribute>
<CType>int</CType>
</RtlPorts>
<RtlPorts>
<name>m_axi_gmem_param_ARREGION</name>
<Object>gmem_param</Object>
<Type>pointer</Type>
<Scope></Scope>
<IOProtocol>m_axi</IOProtocol>
<IOConfig></IOConfig>
<Dir>out</Dir>
<Bits>4</Bits>
<Attribute>unknown</Attribute>
<CType>int</CType>
</RtlPorts>
<RtlPorts>
<name>m_axi_gmem_param_ARUSER</name>
<Object>gmem_param</Object>
<Type>pointer</Type>
<Scope></Scope>
<IOProtocol>m_axi</IOProtocol>
<IOConfig></IOConfig>
<Dir>out</Dir>
<Bits>1</Bits>
<Attribute>unknown</Attribute>
<CType>int</CType>
</RtlPorts>
<RtlPorts>
<name>m_axi_gmem_param_RVALID</name>
<Object>gmem_param</Object>
<Type>pointer</Type>
<Scope></Scope>
<IOProtocol>m_axi</IOProtocol>
<IOConfig></IOConfig>
<Dir>in</Dir>
<Bits>1</Bits>
<Attribute>unknown</Attribute>
<CType>int</CType>
</RtlPorts>
<RtlPorts>
<name>m_axi_gmem_param_RREADY</name>
<Object>gmem_param</Object>
<Type>pointer</Type>
<Scope></Scope>
<IOProtocol>m_axi</IOProtocol>
<IOConfig></IOConfig>
<Dir>out</Dir>
<Bits>1</Bits>
<Attribute>unknown</Attribute>
<CType>int</CType>
</RtlPorts>
<RtlPorts>
<name>m_axi_gmem_param_RDATA</name>
<Object>gmem_param</Object>
<Type>pointer</Type>
<Scope></Scope>
<IOProtocol>m_axi</IOProtocol>
<IOConfig></IOConfig>
<Dir>in</Dir>
<Bits>256</Bits>
<Attribute>unknown</Attribute>
<CType>int</CType>
</RtlPorts>
<RtlPorts>
<name>m_axi_gmem_param_RLAST</name>
<Object>gmem_param</Object>
<Type>pointer</Type>
<Scope></Scope>
<IOProtocol>m_axi</IOProtocol>
<IOConfig></IOConfig>
<Dir>in</Dir>
<Bits>1</Bits>
<Attribute>unknown</Attribute>
<CType>int</CType>
</RtlPorts>
<RtlPorts>
<name>m_axi_gmem_param_RID</name>
<Object>gmem_param</Object>
<Type>pointer</Type>
<Scope></Scope>
<IOProtocol>m_axi</IOProtocol>
<IOConfig></IOConfig>
<Dir>in</Dir>
<Bits>1</Bits>
<Attribute>unknown</Attribute>
<CType>int</CType>
</RtlPorts>
<RtlPorts>
<name>m_axi_gmem_param_RUSER</name>
<Object>gmem_param</Object>
<Type>pointer</Type>
<Scope></Scope>
<IOProtocol>m_axi</IOProtocol>
<IOConfig></IOConfig>
<Dir>in</Dir>
<Bits>1</Bits>
<Attribute>unknown</Attribute>
<CType>int</CType>
</RtlPorts>
<RtlPorts>
<name>m_axi_gmem_param_RRESP</name>
<Object>gmem_param</Object>
<Type>pointer</Type>
<Scope></Scope>
<IOProtocol>m_axi</IOProtocol>
<IOConfig></IOConfig>
<Dir>in</Dir>
<Bits>2</Bits>
<Attribute>unknown</Attribute>
<CType>int</CType>
</RtlPorts>
<RtlPorts>
<name>m_axi_gmem_param_BVALID</name>
<Object>gmem_param</Object>
<Type>pointer</Type>
<Scope></Scope>
<IOProtocol>m_axi</IOProtocol>
<IOConfig></IOConfig>
<Dir>in</Dir>
<Bits>1</Bits>
<Attribute>unknown</Attribute>
<CType>int</CType>
</RtlPorts>
<RtlPorts>
<name>m_axi_gmem_param_BREADY</name>
<Object>gmem_param</Object>
<Type>pointer</Type>
<Scope></Scope>
<IOProtocol>m_axi</IOProtocol>
<IOConfig></IOConfig>
<Dir>out</Dir>
<Bits>1</Bits>
<Attribute>unknown</Attribute>
<CType>int</CType>
</RtlPorts>
<RtlPorts>
<name>m_axi_gmem_param_BRESP</name>
<Object>gmem_param</Object>
<Type>pointer</Type>
<Scope></Scope>
<IOProtocol>m_axi</IOProtocol>
<IOConfig></IOConfig>
<Dir>in</Dir>
<Bits>2</Bits>
<Attribute>unknown</Attribute>
<CType>int</CType>
</RtlPorts>
<RtlPorts>
<name>m_axi_gmem_param_BID</name>
<Object>gmem_param</Object>
<Type>pointer</Type>
<Scope></Scope>
<IOProtocol>m_axi</IOProtocol>
<IOConfig></IOConfig>
<Dir>in</Dir>
<Bits>1</Bits>
<Attribute>unknown</Attribute>
<CType>int</CType>
</RtlPorts>
<RtlPorts>
<name>m_axi_gmem_param_BUSER</name>
<Object>gmem_param</Object>
<Type>pointer</Type>
<Scope></Scope>
<IOProtocol>m_axi</IOProtocol>
<IOConfig></IOConfig>
<Dir>in</Dir>
<Bits>1</Bits>
<Attribute>unknown</Attribute>
<CType>int</CType>
</RtlPorts>
<RtlPorts>
<name>m_axi_gmem_out_AWVALID</name>
<Object>gmem_out</Object>
<Type>pointer</Type>
<Scope></Scope>
<IOProtocol>m_axi</IOProtocol>
<IOConfig></IOConfig>
<Dir>out</Dir>
<Bits>1</Bits>
<Attribute>unknown</Attribute>
<CType>int</CType>
</RtlPorts>
<RtlPorts>
<name>m_axi_gmem_out_AWREADY</name>
<Object>gmem_out</Object>
<Type>pointer</Type>
<Scope></Scope>
<IOProtocol>m_axi</IOProtocol>
<IOConfig></IOConfig>
<Dir>in</Dir>
<Bits>1</Bits>
<Attribute>unknown</Attribute>
<CType>int</CType>
</RtlPorts>
<RtlPorts>
<name>m_axi_gmem_out_AWADDR</name>
<Object>gmem_out</Object>
<Type>pointer</Type>
<Scope></Scope>
<IOProtocol>m_axi</IOProtocol>
<IOConfig></IOConfig>
<Dir>out</Dir>
<Bits>64</Bits>
<Attribute>unknown</Attribute>
<CType>int</CType>
</RtlPorts>
<RtlPorts>
<name>m_axi_gmem_out_AWID</name>
<Object>gmem_out</Object>
<Type>pointer</Type>
<Scope></Scope>
<IOProtocol>m_axi</IOProtocol>
<IOConfig></IOConfig>
<Dir>out</Dir>
<Bits>1</Bits>
<Attribute>unknown</Attribute>
<CType>int</CType>
</RtlPorts>
<RtlPorts>
<name>m_axi_gmem_out_AWLEN</name>
<Object>gmem_out</Object>
<Type>pointer</Type>
<Scope></Scope>
<IOProtocol>m_axi</IOProtocol>
<IOConfig></IOConfig>
<Dir>out</Dir>
<Bits>8</Bits>
<Attribute>unknown</Attribute>
<CType>int</CType>
</RtlPorts>
<RtlPorts>
<name>m_axi_gmem_out_AWSIZE</name>
<Object>gmem_out</Object>
<Type>pointer</Type>
<Scope></Scope>
<IOProtocol>m_axi</IOProtocol>
<IOConfig></IOConfig>
<Dir>out</Dir>
<Bits>3</Bits>
<Attribute>unknown</Attribute>
<CType>int</CType>
</RtlPorts>
<RtlPorts>
<name>m_axi_gmem_out_AWBURST</name>
<Object>gmem_out</Object>
<Type>pointer</Type>
<Scope></Scope>
<IOProtocol>m_axi</IOProtocol>
<IOConfig></IOConfig>
<Dir>out</Dir>
<Bits>2</Bits>
<Attribute>unknown</Attribute>
<CType>int</CType>
</RtlPorts>
<RtlPorts>
<name>m_axi_gmem_out_AWLOCK</name>
<Object>gmem_out</Object>
<Type>pointer</Type>
<Scope></Scope>
<IOProtocol>m_axi</IOProtocol>
<IOConfig></IOConfig>
<Dir>out</Dir>
<Bits>2</Bits>
<Attribute>unknown</Attribute>
<CType>int</CType>
</RtlPorts>
<RtlPorts>
<name>m_axi_gmem_out_AWCACHE</name>
<Object>gmem_out</Object>
<Type>pointer</Type>
<Scope></Scope>
<IOProtocol>m_axi</IOProtocol>
<IOConfig></IOConfig>
<Dir>out</Dir>
<Bits>4</Bits>
<Attribute>unknown</Attribute>
<CType>int</CType>
</RtlPorts>
<RtlPorts>
<name>m_axi_gmem_out_AWPROT</name>
<Object>gmem_out</Object>
<Type>pointer</Type>
<Scope></Scope>
<IOProtocol>m_axi</IOProtocol>
<IOConfig></IOConfig>
<Dir>out</Dir>
<Bits>3</Bits>
<Attribute>unknown</Attribute>
<CType>int</CType>
</RtlPorts>
<RtlPorts>
<name>m_axi_gmem_out_AWQOS</name>
<Object>gmem_out</Object>
<Type>pointer</Type>
<Scope></Scope>
<IOProtocol>m_axi</IOProtocol>
<IOConfig></IOConfig>
<Dir>out</Dir>
<Bits>4</Bits>
<Attribute>unknown</Attribute>
<CType>int</CType>
</RtlPorts>
<RtlPorts>
<name>m_axi_gmem_out_AWREGION</name>
<Object>gmem_out</Object>
<Type>pointer</Type>
<Scope></Scope>
<IOProtocol>m_axi</IOProtocol>
<IOConfig></IOConfig>
<Dir>out</Dir>
<Bits>4</Bits>
<Attribute>unknown</Attribute>
<CType>int</CType>
</RtlPorts>
<RtlPorts>
<name>m_axi_gmem_out_AWUSER</name>
<Object>gmem_out</Object>
<Type>pointer</Type>
<Scope></Scope>
<IOProtocol>m_axi</IOProtocol>
<IOConfig></IOConfig>
<Dir>out</Dir>
<Bits>1</Bits>
<Attribute>unknown</Attribute>
<CType>int</CType>
</RtlPorts>
<RtlPorts>
<name>m_axi_gmem_out_WVALID</name>
<Object>gmem_out</Object>
<Type>pointer</Type>
<Scope></Scope>
<IOProtocol>m_axi</IOProtocol>
<IOConfig></IOConfig>
<Dir>out</Dir>
<Bits>1</Bits>
<Attribute>unknown</Attribute>
<CType>int</CType>
</RtlPorts>
<RtlPorts>
<name>m_axi_gmem_out_WREADY</name>
<Object>gmem_out</Object>
<Type>pointer</Type>
<Scope></Scope>
<IOProtocol>m_axi</IOProtocol>
<IOConfig></IOConfig>
<Dir>in</Dir>
<Bits>1</Bits>
<Attribute>unknown</Attribute>
<CType>int</CType>
</RtlPorts>
<RtlPorts>
<name>m_axi_gmem_out_WDATA</name>
<Object>gmem_out</Object>
<Type>pointer</Type>
<Scope></Scope>
<IOProtocol>m_axi</IOProtocol>
<IOConfig></IOConfig>
<Dir>out</Dir>
<Bits>256</Bits>
<Attribute>unknown</Attribute>
<CType>int</CType>
</RtlPorts>
<RtlPorts>
<name>m_axi_gmem_out_WSTRB</name>
<Object>gmem_out</Object>
<Type>pointer</Type>
<Scope></Scope>
<IOProtocol>m_axi</IOProtocol>
<IOConfig></IOConfig>
<Dir>out</Dir>
<Bits>32</Bits>
<Attribute>unknown</Attribute>
<CType>int</CType>
</RtlPorts>
<RtlPorts>
<name>m_axi_gmem_out_WLAST</name>
<Object>gmem_out</Object>
<Type>pointer</Type>
<Scope></Scope>
<IOProtocol>m_axi</IOProtocol>
<IOConfig></IOConfig>
<Dir>out</Dir>
<Bits>1</Bits>
<Attribute>unknown</Attribute>
<CType>int</CType>
</RtlPorts>
<RtlPorts>
<name>m_axi_gmem_out_WID</name>
<Object>gmem_out</Object>
<Type>pointer</Type>
<Scope></Scope>
<IOProtocol>m_axi</IOProtocol>
<IOConfig></IOConfig>
<Dir>out</Dir>
<Bits>1</Bits>
<Attribute>unknown</Attribute>
<CType>int</CType>
</RtlPorts>
<RtlPorts>
<name>m_axi_gmem_out_WUSER</name>
<Object>gmem_out</Object>
<Type>pointer</Type>
<Scope></Scope>
<IOProtocol>m_axi</IOProtocol>
<IOConfig></IOConfig>
<Dir>out</Dir>
<Bits>1</Bits>
<Attribute>unknown</Attribute>
<CType>int</CType>
</RtlPorts>
<RtlPorts>
<name>m_axi_gmem_out_ARVALID</name>
<Object>gmem_out</Object>
<Type>pointer</Type>
<Scope></Scope>
<IOProtocol>m_axi</IOProtocol>
<IOConfig></IOConfig>
<Dir>out</Dir>
<Bits>1</Bits>
<Attribute>unknown</Attribute>
<CType>int</CType>
</RtlPorts>
<RtlPorts>
<name>m_axi_gmem_out_ARREADY</name>
<Object>gmem_out</Object>
<Type>pointer</Type>
<Scope></Scope>
<IOProtocol>m_axi</IOProtocol>
<IOConfig></IOConfig>
<Dir>in</Dir>
<Bits>1</Bits>
<Attribute>unknown</Attribute>
<CType>int</CType>
</RtlPorts>
<RtlPorts>
<name>m_axi_gmem_out_ARADDR</name>
<Object>gmem_out</Object>
<Type>pointer</Type>
<Scope></Scope>
<IOProtocol>m_axi</IOProtocol>
<IOConfig></IOConfig>
<Dir>out</Dir>
<Bits>64</Bits>
<Attribute>unknown</Attribute>
<CType>int</CType>
</RtlPorts>
<RtlPorts>
<name>m_axi_gmem_out_ARID</name>
<Object>gmem_out</Object>
<Type>pointer</Type>
<Scope></Scope>
<IOProtocol>m_axi</IOProtocol>
<IOConfig></IOConfig>
<Dir>out</Dir>
<Bits>1</Bits>
<Attribute>unknown</Attribute>
<CType>int</CType>
</RtlPorts>
<RtlPorts>
<name>m_axi_gmem_out_ARLEN</name>
<Object>gmem_out</Object>
<Type>pointer</Type>
<Scope></Scope>
<IOProtocol>m_axi</IOProtocol>
<IOConfig></IOConfig>
<Dir>out</Dir>
<Bits>8</Bits>
<Attribute>unknown</Attribute>
<CType>int</CType>
</RtlPorts>
<RtlPorts>
<name>m_axi_gmem_out_ARSIZE</name>
<Object>gmem_out</Object>
<Type>pointer</Type>
<Scope></Scope>
<IOProtocol>m_axi</IOProtocol>
<IOConfig></IOConfig>
<Dir>out</Dir>
<Bits>3</Bits>
<Attribute>unknown</Attribute>
<CType>int</CType>
</RtlPorts>
<RtlPorts>
<name>m_axi_gmem_out_ARBURST</name>
<Object>gmem_out</Object>
<Type>pointer</Type>
<Scope></Scope>
<IOProtocol>m_axi</IOProtocol>
<IOConfig></IOConfig>
<Dir>out</Dir>
<Bits>2</Bits>
<Attribute>unknown</Attribute>
<CType>int</CType>
</RtlPorts>
<RtlPorts>
<name>m_axi_gmem_out_ARLOCK</name>
<Object>gmem_out</Object>
<Type>pointer</Type>
<Scope></Scope>
<IOProtocol>m_axi</IOProtocol>
<IOConfig></IOConfig>
<Dir>out</Dir>
<Bits>2</Bits>
<Attribute>unknown</Attribute>
<CType>int</CType>
</RtlPorts>
<RtlPorts>
<name>m_axi_gmem_out_ARCACHE</name>
<Object>gmem_out</Object>
<Type>pointer</Type>
<Scope></Scope>
<IOProtocol>m_axi</IOProtocol>
<IOConfig></IOConfig>
<Dir>out</Dir>
<Bits>4</Bits>
<Attribute>unknown</Attribute>
<CType>int</CType>
</RtlPorts>
<RtlPorts>
<name>m_axi_gmem_out_ARPROT</name>
<Object>gmem_out</Object>
<Type>pointer</Type>
<Scope></Scope>
<IOProtocol>m_axi</IOProtocol>
<IOConfig></IOConfig>
<Dir>out</Dir>
<Bits>3</Bits>
<Attribute>unknown</Attribute>
<CType>int</CType>
</RtlPorts>
<RtlPorts>
<name>m_axi_gmem_out_ARQOS</name>
<Object>gmem_out</Object>
<Type>pointer</Type>
<Scope></Scope>
<IOProtocol>m_axi</IOProtocol>
<IOConfig></IOConfig>
<Dir>out</Dir>
<Bits>4</Bits>
<Attribute>unknown</Attribute>
<CType>int</CType>
</RtlPorts>
<RtlPorts>
<name>m_axi_gmem_out_ARREGION</name>
<Object>gmem_out</Object>
<Type>pointer</Type>
<Scope></Scope>
<IOProtocol>m_axi</IOProtocol>
<IOConfig></IOConfig>
<Dir>out</Dir>
<Bits>4</Bits>
<Attribute>unknown</Attribute>
<CType>int</CType>
</RtlPorts>
<RtlPorts>
<name>m_axi_gmem_out_ARUSER</name>
<Object>gmem_out</Object>
<Type>pointer</Type>
<Scope></Scope>
<IOProtocol>m_axi</IOProtocol>
<IOConfig></IOConfig>
<Dir>out</Dir>
<Bits>1</Bits>
<Attribute>unknown</Attribute>
<CType>int</CType>
</RtlPorts>
<RtlPorts>
<name>m_axi_gmem_out_RVALID</name>
<Object>gmem_out</Object>
<Type>pointer</Type>
<Scope></Scope>
<IOProtocol>m_axi</IOProtocol>
<IOConfig></IOConfig>
<Dir>in</Dir>
<Bits>1</Bits>
<Attribute>unknown</Attribute>
<CType>int</CType>
</RtlPorts>
<RtlPorts>
<name>m_axi_gmem_out_RREADY</name>
<Object>gmem_out</Object>
<Type>pointer</Type>
<Scope></Scope>
<IOProtocol>m_axi</IOProtocol>
<IOConfig></IOConfig>
<Dir>out</Dir>
<Bits>1</Bits>
<Attribute>unknown</Attribute>
<CType>int</CType>
</RtlPorts>
<RtlPorts>
<name>m_axi_gmem_out_RDATA</name>
<Object>gmem_out</Object>
<Type>pointer</Type>
<Scope></Scope>
<IOProtocol>m_axi</IOProtocol>
<IOConfig></IOConfig>
<Dir>in</Dir>
<Bits>256</Bits>
<Attribute>unknown</Attribute>
<CType>int</CType>
</RtlPorts>
<RtlPorts>
<name>m_axi_gmem_out_RLAST</name>
<Object>gmem_out</Object>
<Type>pointer</Type>
<Scope></Scope>
<IOProtocol>m_axi</IOProtocol>
<IOConfig></IOConfig>
<Dir>in</Dir>
<Bits>1</Bits>
<Attribute>unknown</Attribute>
<CType>int</CType>
</RtlPorts>
<RtlPorts>
<name>m_axi_gmem_out_RID</name>
<Object>gmem_out</Object>
<Type>pointer</Type>
<Scope></Scope>
<IOProtocol>m_axi</IOProtocol>
<IOConfig></IOConfig>
<Dir>in</Dir>
<Bits>1</Bits>
<Attribute>unknown</Attribute>
<CType>int</CType>
</RtlPorts>
<RtlPorts>
<name>m_axi_gmem_out_RUSER</name>
<Object>gmem_out</Object>
<Type>pointer</Type>
<Scope></Scope>
<IOProtocol>m_axi</IOProtocol>
<IOConfig></IOConfig>
<Dir>in</Dir>
<Bits>1</Bits>
<Attribute>unknown</Attribute>
<CType>int</CType>
</RtlPorts>
<RtlPorts>
<name>m_axi_gmem_out_RRESP</name>
<Object>gmem_out</Object>
<Type>pointer</Type>
<Scope></Scope>
<IOProtocol>m_axi</IOProtocol>
<IOConfig></IOConfig>
<Dir>in</Dir>
<Bits>2</Bits>
<Attribute>unknown</Attribute>
<CType>int</CType>
</RtlPorts>
<RtlPorts>
<name>m_axi_gmem_out_BVALID</name>
<Object>gmem_out</Object>
<Type>pointer</Type>
<Scope></Scope>
<IOProtocol>m_axi</IOProtocol>
<IOConfig></IOConfig>
<Dir>in</Dir>
<Bits>1</Bits>
<Attribute>unknown</Attribute>
<CType>int</CType>
</RtlPorts>
<RtlPorts>
<name>m_axi_gmem_out_BREADY</name>
<Object>gmem_out</Object>
<Type>pointer</Type>
<Scope></Scope>
<IOProtocol>m_axi</IOProtocol>
<IOConfig></IOConfig>
<Dir>out</Dir>
<Bits>1</Bits>
<Attribute>unknown</Attribute>
<CType>int</CType>
</RtlPorts>
<RtlPorts>
<name>m_axi_gmem_out_BRESP</name>
<Object>gmem_out</Object>
<Type>pointer</Type>
<Scope></Scope>
<IOProtocol>m_axi</IOProtocol>
<IOConfig></IOConfig>
<Dir>in</Dir>
<Bits>2</Bits>
<Attribute>unknown</Attribute>
<CType>int</CType>
</RtlPorts>
<RtlPorts>
<name>m_axi_gmem_out_BID</name>
<Object>gmem_out</Object>
<Type>pointer</Type>
<Scope></Scope>
<IOProtocol>m_axi</IOProtocol>
<IOConfig></IOConfig>
<Dir>in</Dir>
<Bits>1</Bits>
<Attribute>unknown</Attribute>
<CType>int</CType>
</RtlPorts>
<RtlPorts>
<name>m_axi_gmem_out_BUSER</name>
<Object>gmem_out</Object>
<Type>pointer</Type>
<Scope></Scope>
<IOProtocol>m_axi</IOProtocol>
<IOConfig></IOConfig>
<Dir>in</Dir>
<Bits>1</Bits>
<Attribute>unknown</Attribute>
<CType>int</CType>
</RtlPorts>
</InterfaceSummary>

</profile>
